odoo/addons/l10n_th_fonts/README.rst
odoo/addons/l10n_th_fonts/__init__.py
odoo/addons/l10n_th_fonts/__manifest__.py
odoo/addons/l10n_th_fonts/i18n/l10n_th_fonts.pot
odoo/addons/l10n_th_fonts/models/__init__.py
odoo/addons/l10n_th_fonts/models/res_company.py
odoo/addons/l10n_th_fonts/readme/CONFIGURE.md
odoo/addons/l10n_th_fonts/readme/CONTRIBUTORS.md
odoo/addons/l10n_th_fonts/readme/DESCRIPTION.md
odoo/addons/l10n_th_fonts/static/description/icon.png
odoo/addons/l10n_th_fonts/static/description/index.html
odoo/addons/l10n_th_fonts/static/fonts/AngsanaNew.ttf
odoo/addons/l10n_th_fonts/static/fonts/THBaijam.ttf
odoo/addons/l10n_th_fonts/static/fonts/THChakraPetch.ttf
odoo/addons/l10n_th_fonts/static/fonts/THCharmofAU.ttf
odoo/addons/l10n_th_fonts/static/fonts/THCharmonman.ttf
odoo/addons/l10n_th_fonts/static/fonts/THFahkwang.ttf
odoo/addons/l10n_th_fonts/static/fonts/THK2DJuly8.ttf
odoo/addons/l10n_th_fonts/static/fonts/THKoHo.ttf
odoo/addons/l10n_th_fonts/static/fonts/THKodchasal.ttf
odoo/addons/l10n_th_fonts/static/fonts/THKrub.ttf
odoo/addons/l10n_th_fonts/static/fonts/THMaliGrade6.ttf
odoo/addons/l10n_th_fonts/static/fonts/THNiramitAS.ttf
odoo/addons/l10n_th_fonts/static/fonts/THSarabun.ttf
odoo/addons/l10n_th_fonts/static/fonts/THSarabunNew.ttf
odoo/addons/l10n_th_fonts/static/fonts/THSrisakdi.ttf
odoo/addons/l10n_th_fonts/static/fonts/Webdings.ttf
odoo/addons/l10n_th_fonts/static/src/scss/fonts_style.scss
odoo_addon_l10n_th_fonts-18.0.1.0.0.2.dist-info/METADATA
odoo_addon_l10n_th_fonts-18.0.1.0.0.2.dist-info/WHEEL
odoo_addon_l10n_th_fonts-18.0.1.0.0.2.dist-info/top_level.txt
odoo_addon_l10n_th_fonts-18.0.1.0.0.2.dist-info/RECORD
